ansys/aedt/toolkits/radar_explorer/__init__.py
ansys/aedt/toolkits/radar_explorer/rcs_visualization.py
ansys/aedt/toolkits/radar_explorer/run_toolkit.py
ansys/aedt/toolkits/radar_explorer/backend/__init__.py
ansys/aedt/toolkits/radar_explorer/backend/api.py
ansys/aedt/toolkits/radar_explorer/backend/backend_properties.toml
ansys/aedt/toolkits/radar_explorer/backend/models.py
ansys/aedt/toolkits/radar_explorer/backend/run_backend.py
ansys/aedt/toolkits/radar_explorer/backend/rcs_utils/domain_transforms.py
ansys/aedt/toolkits/radar_explorer/backend/rcs_utils/utils.py
ansys/aedt/toolkits/radar_explorer/ui/__init__.py
ansys/aedt/toolkits/radar_explorer/ui/actions.py
ansys/aedt/toolkits/radar_explorer/ui/frontend_properties.toml
ansys/aedt/toolkits/radar_explorer/ui/models.py
ansys/aedt/toolkits/radar_explorer/ui/run_frontend.py
ansys/aedt/toolkits/radar_explorer/ui/splash.png
ansys/aedt/toolkits/radar_explorer/ui/splash.py
ansys/aedt/toolkits/radar_explorer/ui/utils/widgets/py_line_edit_precision_unit/__init__.py
ansys/aedt/toolkits/radar_explorer/ui/utils/widgets/py_line_edit_precision_unit/py_line_edit_with_float.py
ansys/aedt/toolkits/radar_explorer/ui/utils/widgets/py_line_edit_precision_unit/styles.py
ansys/aedt/toolkits/radar_explorer/ui/windows/__init__.py
ansys/aedt/toolkits/radar_explorer/ui/windows/common_windows_utils.py
ansys/aedt/toolkits/radar_explorer/ui/windows/common_3d_plotter/common_3d_plotter.py
ansys/aedt/toolkits/radar_explorer/ui/windows/help/__init__.py
ansys/aedt/toolkits/radar_explorer/ui/windows/help/help.svg
ansys/aedt/toolkits/radar_explorer/ui/windows/help/help_column.py
ansys/aedt/toolkits/radar_explorer/ui/windows/help/help_column.ui
ansys/aedt/toolkits/radar_explorer/ui/windows/help/help_menu.py
ansys/aedt/toolkits/radar_explorer/ui/windows/help/help_page.py
ansys/aedt/toolkits/radar_explorer/ui/windows/help/help_page.ui
ansys/aedt/toolkits/radar_explorer/ui/windows/home/ANSYS_logo.obj
ansys_aedt_toolkits_radar_explorer-0.1.0.dist-info/licenses/LICENSE
ansys_aedt_toolkits_radar_explorer-0.1.0.dist-info/WHEEL
ansys_aedt_toolkits_radar_explorer-0.1.0.dist-info/METADATA
ansys_aedt_toolkits_radar_explorer-0.1.0.dist-info/RECORD
