Metadata-Version: 2.4
Name: ansys-aedt-toolkits-radar-explorer
Version: 0.1.0
Summary: Toolkit to perform advanced Radar pre and post processing.
Author-email: "ANSYS, Inc." <pyansys.core@ansys.com>
Maintainer-email: "ANSYS, Inc." <pyansys.core@ansys.com>
Requires-Python: >=3.10
License-Expression: Apache-2.0
Classifier: Development Status :: 4 - Beta
Classifier: Intended Audience :: Science/Research
Classifier: Topic :: Scientific/Engineering :: Information Analysis
Classifier: Operating System :: OS Independent
Classifier: Programming Language :: Python :: 3.10
Classifier: Programming Language :: Python :: 3.11
Classifier: Programming Language :: Python :: 3.12
Classifier: Programming Language :: Python :: 3.13
License-File: LICENSE
Requires-Dist: ansys-aedt-toolkits-common[all]
Requires-Dist: ansys-aedt-toolkits-common[doc] ; extra == "doc"
Requires-Dist: pyinstaller ; extra == "freeze"
Requires-Dist: ansys-aedt-toolkits-common[tests] ; extra == "tests"
Project-URL: Changelog, https://github.com/ansys/ansys-aedt-toolkits-radar-explorer/blob/main/doc/source/changelog.rst
Project-URL: Discussions, https://github.com/ansys/ansys-aedt-toolkits-radar-explorer/discussions
Project-URL: Documentation, https://aedt.toolkit.radar.docs.pyansys.com/version/stable/
Project-URL: Issues, https://github.com/ansys/ansys-aedt-toolkits-radar-explorer/issues
Project-URL: Releases, https://github.com/ansys/ansys-aedt-toolkits-radar-explorer/releases
Project-URL: Source, https://github.com/ansys/ansys-aedt-toolkits-radar-explorer.git
Provides-Extra: doc
Provides-Extra: freeze
Provides-Extra: tests
